BIDSit/__init__.py
BIDSit/__main__.py
BIDSit/dicom_to_bids2.py
BIDSit/go.py
BIDSit/go_old.py
BIDSit/version.py
bidsit-0.2.0.dist-info/METADATA
bidsit-0.2.0.dist-info/WHEEL
bidsit-0.2.0.dist-info/entry_points.txt
bidsit-0.2.0.dist-info/top_level.txt
bidsit-0.2.0.dist-info/RECORD
