Metadata-Version: 2.4
Name: BIDSit
Version: 0.2.0
Summary: A BIDS conversion tool for fMRI data
Home-page: https://github.com/jenburrell/BIDSit
Author: Jen Burrell
Author-email: Jen Burrell <jenbur@psych.ubc.ca>
Requires-Python: >=3.9
Requires-Dist: PySimpleGUI<=5.0.0
Requires-Dist: natsort>=8.3.1
Provides-Extra: dev
Requires-Dist: pytest>=3.7; extra == "dev"
Dynamic: author
Dynamic: home-page
Dynamic: requires-python
